cumatfuse/__init__.py
cumatfuse/cumatfuse_ext.cpython-312-x86_64-linux-gnu.so
cumatfuse-0.1.1.dist-info/METADATA
cumatfuse-0.1.1.dist-info/WHEEL
cumatfuse-0.1.1.dist-info/RECORD
