Metadata-Version: 2.2
Name: cumatfuse
Version: 0.1.1
Summary: A high-performance CUDA library for fused matrix multiplication with ReLU
Author-Email: Divakar Yadav <divakar@example.com>
License: MIT
Requires-Python: >=3.8
